sage_timezone/__init__.py
sage_timezone/apps.py
sage_timezone/forms/__init__.py
sage_timezone/forms/timezone.py
sage_timezone/locale/ar/LC_MESSAGES/django.po
sage_timezone/locale/en/LC_MESSAGES/django.po
sage_timezone/locale/fa/LC_MESSAGES/django.po
sage_timezone/middleware/__init__.py
sage_timezone/middleware/timezone.py
sage_timezone/migrations/__init__.py
sage_timezone/templates/admin/base_site.html
sage_timezone/templates/admin/timezone_selection.html
sage_timezone/templatetags/__init__.py
sage_timezone/templatetags/timezone_tags.py
sage_timezone/tests/test_middleware.py
sage_timezone/tests/test_view.py
sage_timezone/urls.py
sage_timezone/views/__init__.py
sage_timezone/views/timezone.py
django_sage_timezone-0.1.3.dist-info/LICENSE
django_sage_timezone-0.1.3.dist-info/METADATA
django_sage_timezone-0.1.3.dist-info/WHEEL
django_sage_timezone-0.1.3.dist-info/RECORD
