Metadata-Version: 2.1
Name: django-sage-timezone
Version: 0.1.3
Summary: A project for timezone handling.
Author: Radin Ghahremani
Author-email: radin@sageteam.org
Requires-Python: >=3.10,<4.0
Classifier: Programming Language :: Python :: 3
Classifier: Programming Language :: Python :: 3.10
Classifier: Programming Language :: Python :: 3.11
Classifier: Programming Language :: Python :: 3.12
Provides-Extra: docs
Requires-Dist: django (>=4.2,<5.0) ; python_version >= "3.8" and python_version < "3.10"
Requires-Dist: django (>=4.2,<5.3) ; python_version >= "3.10"
Requires-Dist: django-sage-tools (>=0.3.2,<0.4.0)
Requires-Dist: pytz (>=2024.1,<2025.0)
